README.txt
setup.py
docs/HISTORY.txt
docs/INSTALL.txt
docs/LICENSE.GPL
docs/LICENSE.txt
docs/TODO.txt
plone/__init__.py
plone.app.archive.egg-info/PKG-INFO
plone.app.archive.egg-info/SOURCES.txt
plone.app.archive.egg-info/dependency_links.txt
plone.app.archive.egg-info/entry_points.txt
plone.app.archive.egg-info/namespace_packages.txt
plone.app.archive.egg-info/not-zip-safe
plone.app.archive.egg-info/requires.txt
plone.app.archive.egg-info/top_level.txt
plone/app/__init__.py
plone/app/archive/__init__.py
plone/app/archive/archive.py
plone/app/archive/configure.zcml
plone/app/archive/interfaces.py
plone/app/archive/tests/__init__.py
plone/app/archive/tests/layer.py
plone/app/archive/tests/test_integration.py