Metadata-Version: 1.0
Name: plone.app.archive
Version: 0.1
Summary: Archive Plone content
Home-page: https://github.com/mjpieters//plone.app.archive
Author: Martijn Pieters
Author-email: mj@jarn.com
License: GPL
Keywords: archiving
Platform: UNKNOWN
Classifier: Framework :: Plone
Classifier: Programming Language :: Python
